phate/__init__.py
phate/cluster.py
phate/io.py
phate/mds.py
phate/phate.py
phate/plot.py
phate/preprocessing.py
phate/tree.py
phate/utils.py
phate/version.py
phate/vne.py
phate-1.0.11.dist-info/METADATA
phate-1.0.11.dist-info/WHEEL
phate-1.0.11.dist-info/top_level.txt
phate-1.0.11.dist-info/RECORD
