Metadata-Version: 2.1
Name: phate
Version: 1.0.11
Summary: PHATE
Home-page: https://github.com/KrishnaswamyLab/PHATE
Download-URL: https://github.com/KrishnaswamyLab/PHATE/archive/v1.0.11.tar.gz
Author: Daniel Burkhardt, Krishnaswamy Lab, Yale University
Author-email: daniel.burkhardt@yale.edu
License: GNU General Public License Version 2
Keywords: visualization,big-data,dimensionality-reduction,embedding,manifold-learning,computational-biology
Classifier: Development Status :: 5 - Production/Stable
Classifier: Environment :: Console
Classifier: Framework :: Jupyter
Classifier: Intended Audience :: Developers
Classifier: Intended Audience :: Science/Research
Classifier: Natural Language :: English
Classifier: Operating System :: MacOS :: MacOS X
Classifier: Operating System :: Microsoft :: Windows
Classifier: Operating System :: POSIX :: Linux
Classifier: Programming Language :: Python :: 3
Classifier: Programming Language :: Python :: 3.5
Classifier: Programming Language :: Python :: 3.6
Classifier: Programming Language :: Python :: 3.7
Classifier: Topic :: Scientific/Engineering :: Bio-Informatics
Classifier: Topic :: Scientific/Engineering :: Visualization
Requires-Dist: numpy (>=1.16.0)
Requires-Dist: scipy (>=1.1.0)
Requires-Dist: scikit-learn (>=0.20.0)
Requires-Dist: future
Requires-Dist: tasklogger (>=1.2)
Requires-Dist: graphtools (>=1.5.3)
Requires-Dist: scprep (>=0.11.1)
Requires-Dist: Deprecated
Requires-Dist: s-gd2 (>=1.8.1)
Requires-Dist: matplotlib (>=3.0)
Provides-Extra: doc
Requires-Dist: sphinx ; extra == 'doc'
Requires-Dist: sphinxcontrib-napoleon ; extra == 'doc'
Provides-Extra: test
Requires-Dist: nose2 ; extra == 'test'
Requires-Dist: anndata ; extra == 'test'
Requires-Dist: coverage ; extra == 'test'
Requires-Dist: coveralls ; extra == 'test'
Requires-Dist: nose ; extra == 'test'
